[{"line":2,"elements":[{"start_timestamp":"2023-03-05T08:27:26.475Z","line":35,"name":"log-in with empty username and valid password","description":"","id":"my-account-login;log-in-with-empty-username-and-valid-password","type":"scenario","keyword":"Scenario","steps":[{"result":{"duration":16906772200,"status":"passed"},"line":36,"name":"user go to \"http://practice.automationtesting.in/\"","match":{"arguments":[{"val":"\"http://practice.automationtesting.in/\"","offset":11}],"location":"stepdefinitions.MyAccountLoginStepDefinitions.Login1_StepDefinitions.user_go_to(java.lang.String)"},"keyword":"Given "},{"result":{"duration":140909100,"status":"passed"},"line":37,"name":"user click on My Account Menu","match":{"location":"stepdefinitions.MyAccountLoginStepDefinitions.Login1_StepDefinitions.user_click_on_my_account_menu()"},"keyword":"When "},{"result":{"duration":6325196800,"status":"passed"},"line":38,"name":"user enter empty username in username-textbox","match":{"location":"stepdefinitions.MyAccountLoginStepDefinitions.Login4_StepDefinitions.user_enter_empty_username_in_username_textbox()"},"keyword":"Then "},{"result":{"duration":109932200,"status":"passed"},"line":39,"name":"user enter valid password in the password textbox","match":{"location":"stepdefinitions.MyAccountLoginStepDefinitions.Login4_StepDefinitions.user_enter_valid_password_in_the_password_textbox()"},"keyword":"Then "},{"result":{"duration":1623568900,"status":"passed"},"line":40,"name":"user click on login button","match":{"location":"stepdefinitions.MyAccountLoginStepDefinitions.Login1_StepDefinitions.user_click_on_login_button()"},"keyword":"Then "},{"result":{"duration":95940400,"status":"passed"},"line":41,"name":"user must verify error message (Invalid username)","match":{"location":"stepdefinitions.MyAccountLoginStepDefinitions.Login4_StepDefinitions.userMustVerifyErrorMessageInvalidUsername()"},"keyword":"Then "},{"result":{"duration":446890200,"status":"passed"},"line":42,"name":"user close driver","match":{"location":"stepdefinitions.MyAccountLoginStepDefinitions.Login1_StepDefinitions.userCloseDriver()"},"keyword":"And "}],"tags":[{"name":"@myaccount_login"},{"name":"@testrunner"}]}],"name":"My Account-Login","description":"","id":"my-account-login","keyword":"Feature","uri":"file:src/test/resources/features/my_account_login.feature","tags":[{"name":"@myaccount_login","type":"Tag","location":{"line":1,"column":1}}]}]